{
  "frn": 523180,
  "name": "Artemis Investment Management LLP",
  "trading_names": [
    null,
    null
  ],
  "appointed_reps": [],
  "individuals": [],
  "person_metadata": {},
  "controlled_functions": {},
  "metadata": {
    "frn": "523180",
    "organisation_name": "Artemis Investment Management LLP",
    "status": "Authorised",
    "business_type": "Regulated",
    "companies_house_number": "OC354068",
    "system_timestamp": "23/06/2025 21:54",
    "status_effective_date": "01/10/2010"
  },
  "person_records": {}
}