{
  "frn": 483062,
  "metadata": {
    "frn": "483062",
    "organisation_name": "Clearwater Corporate Finance LLP",
    "status": "Authorised",
    "status_effective_date": "24/07/2008",
    "business_type": "Regulated",
    "system_timestamp": "20/07/2025 18:18",
    "companies_house_number": "OC311299",
    "exceptions": [],
    "_links": {
      "names": null,
      "individuals": "https://register.fca.org.uk/services/V0.1/Firm/483062/Individuals",
      "requirements": "https://register.fca.org.uk/services/V0.1/Firm/483062/Requirements",
      "permissions": null,
      "passport": "https://register.fca.org.uk/services/V0.1/Firm/483062/Passports",
      "regulators": "https://register.fca.org.uk/services/V0.1/Firm/483062/Regulators",
      "appointed_reps": "https://register.fca.org.uk/services/V0.1/Firm/483062/AR",
      "address": "https://register.fca.org.uk/services/V0.1/Firm/483062/Address",
      "waivers": "https://register.fca.org.uk/services/V0.1/Firm/483062/Waivers",
      "exclusions": "https://register.fca.org.uk/services/V0.1/Firm/483062/Exclusions",
      "disciplinary_history": "https://register.fca.org.uk/services/V0.1/Firm/483062/DisciplinaryHistory"
    }
  },
  "trading_names": [
    null,
    null
  ],
  "appointed_reps": [],
  "individuals": [],
  "person_records": {},
  "controlled_functions": {}
}