{
  "frn": 602082,
  "name": "Currency Solutions Limited",
  "trading_names": [
    null
  ],
  "appointed_reps": {
    "PreviousAppointedRepresentatives": [
      {
        "URL": "https://register.fca.org.uk/services/V0.1/Firm/939613",
        "Termination Date": "20/12/2024",
        "RecordSubType": "Introducer",
        "Principal FRN": "602082",
        "Principal Firm Name": "Currency Solutions Limited",
        "Effective Date": "16/06/2023",
        "EEA Tied Agent": "false",
        "Tied Agent": "false",
        "[NotinUse] Insurance Distribution": "false",
        "FRN": "939613",
        "Name": "Jackson Swiss Partners Trading Limited"
      }
    ],
    "CurrentAppointedRepresentatives": null
  },
  "individuals": [],
  "person_metadata": {},
  "controlled_functions": {},
  "metadata": {
    "frn": "602082",
    "organisation_name": "Currency Solutions Limited",
    "status": "Authorised",
    "business_type": "Regulated",
    "companies_house_number": "04864491",
    "system_timestamp": "23/06/2025 22:00",
    "status_effective_date": "01/04/2014"
  },
  "person_records": {}
}