{
  "frn": 607652,
  "metadata": {
    "frn": "607652",
    "organisation_name": "Curzon Advisers Limited",
    "status": "Authorised",
    "status_effective_date": "20/06/2014",
    "business_type": "Regulated",
    "system_timestamp": "20/07/2025 18:09",
    "companies_house_number": "08613931",
    "exceptions": [],
    "_links": {
      "names": null,
      "individuals": "https://register.fca.org.uk/services/V0.1/Firm/607652/Individuals",
      "requirements": "https://register.fca.org.uk/services/V0.1/Firm/607652/Requirements",
      "permissions": null,
      "passport": "https://register.fca.org.uk/services/V0.1/Firm/607652/Passports",
      "regulators": "https://register.fca.org.uk/services/V0.1/Firm/607652/Regulators",
      "appointed_reps": "https://register.fca.org.uk/services/V0.1/Firm/607652/AR",
      "address": "https://register.fca.org.uk/services/V0.1/Firm/607652/Address",
      "waivers": "https://register.fca.org.uk/services/V0.1/Firm/607652/Waivers",
      "exclusions": "https://register.fca.org.uk/services/V0.1/Firm/607652/Exclusions",
      "disciplinary_history": "https://register.fca.org.uk/services/V0.1/Firm/607652/DisciplinaryHistory"
    }
  },
  "trading_names": [
    null
  ],
  "appointed_reps": [],
  "individuals": [],
  "person_records": {},
  "controlled_functions": {}
}