{
  "frn": 401821,
  "metadata": {
    "frn": "401821",
    "organisation_name": "Davidson Kempner European Partners, LLP",
    "status": "Authorised",
    "status_effective_date": "07/10/2004",
    "business_type": "Regulated",
    "system_timestamp": "20/07/2025 18:08",
    "companies_house_number": "OC308054",
    "exceptions": [],
    "_links": {
      "names": null,
      "individuals": "https://register.fca.org.uk/services/V0.1/Firm/401821/Individuals",
      "requirements": "https://register.fca.org.uk/services/V0.1/Firm/401821/Requirements",
      "permissions": null,
      "passport": "https://register.fca.org.uk/services/V0.1/Firm/401821/Passports",
      "regulators": "https://register.fca.org.uk/services/V0.1/Firm/401821/Regulators",
      "appointed_reps": "https://register.fca.org.uk/services/V0.1/Firm/401821/AR",
      "address": "https://register.fca.org.uk/services/V0.1/Firm/401821/Address",
      "waivers": "https://register.fca.org.uk/services/V0.1/Firm/401821/Waivers",
      "exclusions": "https://register.fca.org.uk/services/V0.1/Firm/401821/Exclusions",
      "disciplinary_history": "https://register.fca.org.uk/services/V0.1/Firm/401821/DisciplinaryHistory"
    }
  },
  "trading_names": [
    null,
    null
  ],
  "appointed_reps": [],
  "individuals": [],
  "person_records": {},
  "controlled_functions": {}
}