{
  "frn": 949232,
  "name": "Delft Investments Limited",
  "trading_names": [
    null,
    null
  ],
  "appointed_reps": [],
  "individuals": [],
  "person_metadata": {},
  "controlled_functions": {},
  "metadata": {
    "frn": "949232",
    "organisation_name": "Delft Investments Limited",
    "status": "Authorised",
    "business_type": "Regulated",
    "companies_house_number": "12952526",
    "system_timestamp": "23/06/2025 22:19",
    "status_effective_date": "01/10/2021"
  },
  "person_records": {}
}