{
  "frn": 925160,
  "name": "Fairhall Investments Ltd",
  "trading_names": [
    null
  ],
  "appointed_reps": [],
  "individuals": [],
  "person_metadata": {},
  "controlled_functions": {},
  "metadata": {
    "frn": "925160",
    "organisation_name": "Fairhall Investments Ltd",
    "status": "Authorised",
    "business_type": "Regulated",
    "companies_house_number": "08093040",
    "system_timestamp": "23/06/2025 22:17",
    "status_effective_date": "23/09/2020"
  },
  "person_records": {}
}