{
  "frn": 673574,
  "name": "Genpact WM UK Limited",
  "trading_names": [
    null,
    null
  ],
  "appointed_reps": {
    "PreviousAppointedRepresentatives": null,
    "CurrentAppointedRepresentatives": [
      {
        "URL": "https://register.fca.org.uk/services/V0.1/Firm/1023349",
        "RecordSubType": "Full",
        "Principal FRN": "673574",
        "Principal Firm Name": "Genpact WM UK Limited",
        "Effective Date": "15/01/2025",
        "EEA Tied Agent": "false",
        "Tied Agent": "false",
        "[NotinUse] Insurance Distribution": "false",
        "FRN": "1023349",
        "Name": "Genpact India Private Limited"
      }
    ]
  },
  "individuals": [],
  "person_metadata": {},
  "controlled_functions": {},
  "metadata": {
    "frn": "673574",
    "organisation_name": "Genpact WM UK Limited",
    "status": "Authorised",
    "business_type": "Regulated",
    "companies_house_number": "09306696",
    "system_timestamp": "23/06/2025 22:06",
    "status_effective_date": "22/06/2015"
  },
  "person_records": {}
}