{
  "frn": 506903,
  "name": "Global Infrastructure Management LLP",
  "trading_names": [
    null
  ],
  "appointed_reps": [],
  "individuals": [],
  "person_metadata": {},
  "controlled_functions": {},
  "metadata": {
    "frn": "506903",
    "organisation_name": "Global Infrastructure Management LLP",
    "status": "Authorised",
    "business_type": "Regulated",
    "companies_house_number": "OC347017",
    "system_timestamp": "23/06/2025 21:53",
    "status_effective_date": "24/12/2009"
  },
  "person_records": {}
}