{
  "frn": 930336,
  "name": "Hythe Bay Metals Limited",
  "trading_names": [
    null,
    null
  ],
  "appointed_reps": [],
  "individuals": [],
  "person_metadata": {},
  "controlled_functions": {},
  "metadata": {
    "frn": "930336",
    "organisation_name": "Hythe Bay Metals Limited",
    "status": "Authorised",
    "business_type": "Regulated",
    "companies_house_number": "12312086",
    "system_timestamp": "23/06/2025 22:18",
    "status_effective_date": "13/11/2020"
  },
  "person_records": {}
}