{
  "frn": 121857,
  "metadata": {},
  "trading_names": [
    null,
    null
  ],
  "appointed_reps": {
    "PreviousAppointedRepresentatives": [
      {
        "URL": "https://register.fca.org.uk/services/V0.1/Firm/205630",
        "Termination Date": "05/04/2012",
        "RecordSubType": "Full",
        "Principal FRN": "121857",
        "Principal Firm Name": "Janus Henderson Investors UK Limited",
        "Effective Date": "03/11/1997",
        "EEA Tied Agent": "false",
        "Tied Agent": "false",
        "[NotinUse] Insurance Distribution": "false",
        "FRN": "205630",
        "Name": "Henderson Real Estate Strategy Limited"
      }
    ],
    "CurrentAppointedRepresentatives": null
  },
  "individuals": [],
  "person_records": {},
  "controlled_functions": {}
}