{
  "frn": 122703,
  "metadata": {},
  "trading_names": [
    null,
    null
  ],
  "appointed_reps": {
    "PreviousAppointedRepresentatives": [
      {
        "URL": "https://register.fca.org.uk/services/V0.1/Firm/626450",
        "Termination Date": "06/04/2016",
        "RecordSubType": "Full",
        "Principal FRN": "122703",
        "Principal Firm Name": "NOMURA ASSET MANAGEMENT U.K. LIMITED",
        "Effective Date": "24/06/2014",
        "EEA Tied Agent": "false",
        "Tied Agent": "false",
        "[NotinUse] Insurance Distribution": "false",
        "FRN": "626450",
        "Name": "Philip Jowett"
      }
    ],
    "CurrentAppointedRepresentatives": null
  },
  "individuals": [],
  "person_records": {},
  "controlled_functions": {}
}