{
  "frn": 950964,
  "name": "Privalgo Markets Limited",
  "trading_names": [
    null
  ],
  "appointed_reps": [],
  "individuals": [],
  "person_metadata": {},
  "controlled_functions": {},
  "metadata": {
    "frn": "950964",
    "organisation_name": "Privalgo Markets Limited",
    "status": "Authorised",
    "business_type": "Regulated",
    "companies_house_number": "11219560",
    "system_timestamp": "23/06/2025 22:19",
    "status_effective_date": "10/05/2022"
  },
  "person_records": {}
}