{
  "frn": 748322,
  "name": "Proterra Investment Partners LLP",
  "trading_names": [
    null
  ],
  "appointed_reps": [],
  "individuals": [],
  "person_metadata": {},
  "controlled_functions": {},
  "metadata": {
    "frn": "748322",
    "organisation_name": "Proterra Investment Partners LLP",
    "status": "Authorised",
    "business_type": "Regulated",
    "companies_house_number": "OC402462",
    "system_timestamp": "23/06/2025 22:09",
    "status_effective_date": "04/10/2016"
  },
  "person_records": {}
}