{
  "frn": 572243,
  "name": "QIC European Investment Services Limited",
  "trading_names": [
    null
  ],
  "appointed_reps": [],
  "individuals": [],
  "person_metadata": {},
  "controlled_functions": {},
  "metadata": {
    "frn": "572243",
    "organisation_name": "QIC European Investment Services Limited",
    "status": "Authorised",
    "business_type": "Regulated",
    "companies_house_number": "07804418",
    "system_timestamp": "23/06/2025 21:57",
    "status_effective_date": "16/05/2012"
  },
  "person_records": {}
}