{
  "frn": 583325,
  "metadata": {
    "frn": "583325",
    "organisation_name": "Technology Crossover Ventures UK, LLP",
    "status": "Authorised",
    "status_effective_date": "28/08/2012",
    "business_type": "Regulated",
    "system_timestamp": "20/07/2025 18:18",
    "companies_house_number": "OC375145",
    "exceptions": [],
    "_links": {
      "names": null,
      "individuals": "https://register.fca.org.uk/services/V0.1/Firm/583325/Individuals",
      "requirements": "https://register.fca.org.uk/services/V0.1/Firm/583325/Requirements",
      "permissions": null,
      "passport": "https://register.fca.org.uk/services/V0.1/Firm/583325/Passports",
      "regulators": "https://register.fca.org.uk/services/V0.1/Firm/583325/Regulators",
      "appointed_reps": "https://register.fca.org.uk/services/V0.1/Firm/583325/AR",
      "address": "https://register.fca.org.uk/services/V0.1/Firm/583325/Address",
      "waivers": "https://register.fca.org.uk/services/V0.1/Firm/583325/Waivers",
      "exclusions": "https://register.fca.org.uk/services/V0.1/Firm/583325/Exclusions",
      "disciplinary_history": "https://register.fca.org.uk/services/V0.1/Firm/583325/DisciplinaryHistory"
    }
  },
  "trading_names": [
    null
  ],
  "appointed_reps": [],
  "individuals": [],
  "person_records": {},
  "controlled_functions": {}
}