{
  "frn": 183210,
  "name": "Torevell & Partners Limited",
  "trading_names": [
    null,
    null
  ],
  "appointed_reps": [],
  "individuals": [],
  "person_metadata": {},
  "controlled_functions": {},
  "metadata": {
    "frn": "183210",
    "organisation_name": "Torevell & Partners Limited",
    "status": "See full details",
    "business_type": "Regulated",
    "companies_house_number": "03279315",
    "system_timestamp": "23/06/2025 21:39",
    "status_effective_date": "01/12/2001"
  },
  "person_records": {}
}